pgvector_template/__init__.py
pgvector_template/types.py
pgvector_template/core/__init__.py
pgvector_template/core/document.py
pgvector_template/core/embedder.py
pgvector_template/core/manager.py
pgvector_template/core/search.py
pgvector_template/db/__init__.py
pgvector_template/db/connection.py
pgvector_template/db/document_db.py
pgvector_template/models/__init__.py
pgvector_template/models/search.py
pgvector_template/service/__init__.py
pgvector_template/service/document_service.py
pgvector_template/utils/__init__.py
pgvector_template/utils/metadata_filter.py
pgvector_template-0.3.4.dist-info/licenses/LICENSE
pgvector_template-0.3.4.dist-info/METADATA
pgvector_template-0.3.4.dist-info/WHEEL
pgvector_template-0.3.4.dist-info/top_level.txt
pgvector_template-0.3.4.dist-info/RECORD
